{
	"dialogue": [
		{
			"sound": "",
			"speed": 0.05,
			"portrait": "bf",
			"boxState": "normal",
			"expression": "talk",
			"text": "damn, what a fucking darkness"
		},
		{
			"sound": "",
			"speed": 0.05,
			"portrait": "bf",
			"boxState": "normal",
			"expression": "talk",
			"text": "hello??? Anyone there? Guarey??"
		},
		{
			"sound": "",
			"speed": 0.05,
			"portrait": "bf",
			"boxState": "normal",
			"expression": "talk",
			"text": "*LIGHS TURN ON*"
		},
		{
			"sound": "",
			"speed": 0.05,
			"portrait": "bf",
			"boxState": "normal",
			"expression": "talk",
			"text": "WHAT THE FUCK IS A ROBOT HERE!"
		},
		{
			"sound": "",
			"speed": 0.05,
			"portrait": "bf",
			"boxState": "normal",
			"expression": "talk",
			"text": "Singing robot?"
		},
		{
			"sound": "",
			"speed": 0.05,
			"portrait": "bf",
			"boxState": "normal",
			"expression": "talk",
			"text": "Strange I've never seen a robot like this... was made by Daddy Dearest"
		},
		{
			"sound": "",
			"speed": 0.05,
			"portrait": "bf",
			"boxState": "normal",
			"expression": "talk",
			"text": "coolswag"
		},
		{
			"sound": "",
			"speed": 0.05,
			"portrait": "bf",
			"boxState": "normal",
			"expression": "talk",
			"text": "Chapter 1: Singing with a Robot in Nevada"
		}
	]
}